yfoptions_dl/__init__.py
yfoptions_dl/yfoptions_dl.py
yfoptions_dl-1.0.2.dist-info/METADATA
yfoptions_dl-1.0.2.dist-info/WHEEL
yfoptions_dl-1.0.2.dist-info/top_level.txt
yfoptions_dl-1.0.2.dist-info/RECORD
