Metadata-Version: 2.1
Name: yfoptions-dl
Version: 1.0.2
Summary: Download option chain data from Yahoo Finance
Home-page: https://github.com/jingzact/yfoptions_dl
Author: Jay
Author-email: pythoninoffice@gmail.com
License: MIT
Platform: UNKNOWN
Classifier: License :: OSI Approved :: MIT License
Classifier: Programming Language :: Python :: 3
Classifier: Programming Language :: Python :: 3.7
Requires-Dist: pandas (>=1.0.0)
Requires-Dist: requests (>2.23.0)
